imageTech/__init__.py
imageTech/image_deduplication.py
imageTech/image_syncer.py
imageTech/logs.py
imageTech/utils.py
tests/__init__.py
tests/test_image_syncer.py
imageTech-1.0.0.dist-info/LICENSE
imageTech-1.0.0.dist-info/METADATA
imageTech-1.0.0.dist-info/WHEEL
imageTech-1.0.0.dist-info/top_level.txt
imageTech-1.0.0.dist-info/RECORD
