Metadata-Version: 2.1
Name: imageTech
Version: 1.0.0
Summary: Python Library to process and compare images.
Author: Sarthak, Harshit
Author-email: sarthak6jan16@gmail.com
License: MIT
Classifier: License :: OSI Approved :: MIT License
Classifier: Programming Language :: Python
Classifier: Programming Language :: Python :: 3
Classifier: Topic :: Software Development :: Libraries
Requires-Python: >=3.6
License-File: LICENSE
Requires-Dist: opencv-python
Requires-Dist: pillow
Requires-Dist: pytest
